README.md
setup.py
codefarmer/__init__.py
codefarmer/modelmix.py
codefarmer/stepbystep.py
codefarmer.egg-info/PKG-INFO
codefarmer.egg-info/SOURCES.txt
codefarmer.egg-info/dependency_links.txt
codefarmer.egg-info/requires.txt
codefarmer.egg-info/top_level.txt