Metadata-Version: 1.2
Name: codefarmer
Version: 2.0.0
Summary: ccf contest
Home-page: UNKNOWN
Author: cyq
Author-email: 596871173@qq.com
License: we are the champion
Platform: any
Requires-Python: >=3.5.0
